nacos_sdk_python-3.0.4.dist-info/licenses/LICENSE
v2/__init__.py
v2/nacos/__init__.py
v2/nacos/nacos_client.py
v2/nacos/ai/__init__.py
v2/nacos/ai/nacos_ai_service.py
v2/nacos/ai/model/__init__.py
v2/nacos/ai/model/ai_constant.py
v2/nacos/ai/model/ai_param.py
v2/nacos/ai/model/ai_request.py
v2/nacos/ai/model/ai_response.py
v2/nacos/ai/model/a2a/__init__.py
v2/nacos/ai/model/a2a/a2a.py
v2/nacos/ai/model/cache/__init__.py
v2/nacos/ai/model/cache/agent_info_cache.py
v2/nacos/ai/model/cache/agent_subscribe_manager.py
v2/nacos/ai/model/cache/mcp_server_info_cache.py
v2/nacos/ai/model/cache/mcp_server_subscribe_manager.py
v2/nacos/ai/model/mcp/__init__.py
v2/nacos/ai/model/mcp/mcp.py
v2/nacos/ai/model/mcp/registry.py
v2/nacos/ai/redo/__init__.py
v2/nacos/ai/redo/ai_grpc_redo_service.py
v2/nacos/ai/redo/ai_redo_data.py
v2/nacos/ai/remote/__init__.py
v2/nacos/ai/remote/ai_grpc_client_proxy.py
v2/nacos/ai/util/__init__.py
v2/nacos/ai/util/agent_util.py
v2/nacos/ai/util/mcp_server_util.py
v2/nacos/common/__init__.py
v2/nacos/common/auth.py
v2/nacos/common/client_config.py
v2/nacos/common/client_config_builder.py
v2/nacos/common/constants.py
v2/nacos/common/nacos_exception.py
v2/nacos/common/payload_registry.py
v2/nacos/common/preserved_metadata_key.py
v2/nacos/config/__init__.py
v2/nacos/config/nacos_config_service.py
v2/nacos/config/cache/__init__.py
v2/nacos/config/cache/config_info_cache.py
v2/nacos/config/cache/config_subscribe_manager.py
v2/nacos/config/encryption/__init__.py
v2/nacos/config/encryption/kms_client.py
v2/nacos/config/encryption/kms_handler.py
v2/nacos/config/encryption/plugin/__init__.py
v2/nacos/config/encryption/plugin/encryption_plugin.py
v2/nacos/config/encryption/plugin/kms_aes_128_encrytion_plugin.py
v2/nacos/config/encryption/plugin/kms_aes_256_encrytion_plugin.py
v2/nacos/config/encryption/plugin/kms_base_encryption_plugin.py
v2/nacos/config/encryption/plugin/kms_encrytion_plugin.py
v2/nacos/config/filter/__init__.py
v2/nacos/config/filter/config_encryption_filter.py
nacos_sdk_python-3.0.4.dist-info/METADATA
nacos_sdk_python-3.0.4.dist-info/WHEEL
nacos_sdk_python-3.0.4.dist-info/top_level.txt
nacos_sdk_python-3.0.4.dist-info/RECORD
