Metadata-Version: 2.4
Name: nacos-sdk-python
Version: 3.0.4
Summary: Python client for Nacos.
Home-page: https://github.com/nacos-group/nacos-sdk-python
Author: nacos
Author-email: 755063194@qq.com
License: Apache License 2.0
Project-URL: Documentation, https://github.com/nacos-group/nacos-sdk-python
Project-URL: Source, https://github.com/nacos-group/nacos-sdk-python
Project-URL: Nacos Open API Guide, https://nacos.io/en-us/docs/open-api.html
Keywords: nacos,nacos-sdk-python
Classifier: Topic :: Software Development :: Libraries :: Python Modules
Classifier: Operating System :: OS Independent
Classifier: Programming Language :: Python
Classifier: Programming Language :: Python :: 3
Classifier: Programming Language :: Python :: 3.10
Classifier: Programming Language :: Python :: 3.11
Classifier: Programming Language :: Python :: 3.12
Classifier: Programming Language :: Python :: 3.13
Requires-Python: >=3.10
License-File: LICENSE
Requires-Dist: aiofiles>=24.1.0
Requires-Dist: aiohttp>=3.10.11
Requires-Dist: alibabacloud_kms20160120>=2.2.3
Requires-Dist: alibabacloud_tea_openapi>=0.3.12
Requires-Dist: grpcio>=1.66.1
Requires-Dist: protobuf>=3.20.3
Requires-Dist: psutil>=5.9.5
Requires-Dist: pycryptodome>=3.19.1
Requires-Dist: pydantic>=2.10.4
Requires-Dist: a2a>=0.44
Requires-Dist: a2a-sdk>=0.3.20
Dynamic: author
Dynamic: author-email
Dynamic: classifier
Dynamic: description
Dynamic: description-content-type
Dynamic: home-page
Dynamic: keywords
Dynamic: license
Dynamic: license-file
Dynamic: project-url
Dynamic: requires-dist
Dynamic: requires-python
Dynamic: summary
